dicomsorter/__init__.py
dicomsorter/cli.py
dicomsorter/config.py
dicomsorter/dicom_utils.py
dicomsorter/dicomsorter.py
dicomsorter/errors.py
dicomsorter/utils.py
dicomsorter-0.1.0a4.dist-info/LICENSE
dicomsorter-0.1.0a4.dist-info/METADATA
dicomsorter-0.1.0a4.dist-info/WHEEL
dicomsorter-0.1.0a4.dist-info/entry_points.txt
dicomsorter-0.1.0a4.dist-info/top_level.txt
dicomsorter-0.1.0a4.dist-info/RECORD
