Metadata-Version: 2.1
Name: dicomsorter
Version: 0.1.0a4
Summary: Python library for sorting DICOM images
Home-page: https://github.com/dicomsort/dicomsorter
Author: Jonathan Suever
Author-email: suever@gmail.com
License: MIT
Keywords: dicom medical images
Platform: UNKNOWN
Classifier: Development Status :: 3 - Alpha
Classifier: Intended Audience :: Developers
Classifier: Topic :: Software Development :: Build Tools
Classifier: License :: OSI Approved :: MIT License
Classifier: Programming Language :: Python :: 2
Classifier: Programming Language :: Python :: 2.7
Classifier: Programming Language :: Python :: 3
Classifier: Programming Language :: Python :: 3.3
Classifier: Programming Language :: Python :: 3.4
Classifier: Programming Language :: Python :: 3.5
Classifier: Operating System :: OS Independent
Requires-Dist: fasteners (>=0.14)
Requires-Dist: pathlib
Requires-Dist: pathos (>=0.2)
Requires-Dist: pydicom (==1.2.0)
Requires-Dist: tqdm (>=4.28)
